<?xml version="1.0" encoding="UTF-8"?>
<objects serializationModel="Studio.02.02.00">
	<object class="AudioFile" id="{4fd6d997-1163-4b93-9d3c-d42521ed9155}">
		<property name="assetPath">
			<value>En_VL_Idle009.ogg</value>
		</property>
		<property name="frequencyInKHz">
			<value>44.0999985</value>
		</property>
		<property name="channelCount">
			<value>1</value>
		</property>
		<property name="length">
			<value>4.9399773242630385</value>
		</property>
		<relationship name="masterAssetFolder">
			<destination>{48f88e92-0dbd-4eae-9bef-3fe94893f18d}</destination>
		</relationship>
	</object>
</objects>
